breakfast/__init__.py
breakfast/breakfast.py
breakfast/cache.py
breakfast/console.py
breakfast-0.4.6.dist-info/LICENSE
breakfast-0.4.6.dist-info/METADATA
breakfast-0.4.6.dist-info/WHEEL
breakfast-0.4.6.dist-info/entry_points.txt
breakfast-0.4.6.dist-info/RECORD
