Metadata-Version: 2.3
Name: breakfast
Version: 0.4.6
Summary: Fast putative outbreak cluster and infection chain detection using SNPs.
License: MIT
Author: Matthew Huska
Author-email: HuskaM@rki.de
Requires-Python: >=3.11,<3.13
Classifier: License :: OSI Approved :: MIT License
Classifier: Programming Language :: Python :: 3
Classifier: Programming Language :: Python :: 3.11
Classifier: Programming Language :: Python :: 3.12
Requires-Dist: click (>=8.1.7,<9.0.0)
Requires-Dist: networkx (>=3.4.2,<4.0.0)
Requires-Dist: numpy (>=2.1.3,<3.0.0)
Requires-Dist: pandas (>=2.2.3,<3.0.0)
Requires-Dist: scikit-learn (>=1.5.2,<2.0.0)
Requires-Dist: scipy (>=1.14.1,<2.0.0)
Project-URL: Repository, https://github.com/rki-mf1/breakfast
